Metadata-Version: 2.1
Name: OpenCV-Edge-Detection
Version: 0.0.1
Summary: A package to detect edges in camera
Author: Kautilya Katariya
